setup.py
alibabacloud_openapi_paginator/__init__.py
alibabacloud_openapi_paginator/client.py
alibabacloud_openapi_paginator/models.py
alibabacloud_openapi_paginator.egg-info/PKG-INFO
alibabacloud_openapi_paginator.egg-info/SOURCES.txt
alibabacloud_openapi_paginator.egg-info/dependency_links.txt
alibabacloud_openapi_paginator.egg-info/requires.txt
alibabacloud_openapi_paginator.egg-info/top_level.txt